[
  {
    "term": "ameliorate",
    "language": "en",
    "partOfSpeech": "verb",
    "status": "enriched",
    "meanings": [
      {
        "definition": "To make something bad or unsatisfactory better or more tolerable.",
        "example": "The new policy was designed to ameliorate the housing crisis affecting low-income families.",
        "register": "formal",
        "tags": [
          "C1"
        ]
      }
    ],
    "synonyms": [
      "improve",
      "alleviate",
      "mitigate"
    ],
    "antonymTerms": [],
    "relatedTerms": [],
    "translation": null
  },
  {
    "term": "concomitant",
    "language": "en",
    "partOfSpeech": "adjective",
    "status": "enriched",
    "meanings": [
      {
        "definition": "Naturally accompanying or associated with something; occurring together.",
        "example": "Rapid industrialisation brought concomitant problems of pollution and urban overcrowding.",
        "register": "formal",
        "tags": [
          "C1"
        ]
      }
    ],
    "synonyms": [
      "accompanying",
      "attendant",
      "concurrent"
    ],
    "antonymTerms": [],
    "relatedTerms": [],
    "translation": null
  },
  {
    "term": "deleterious",
    "language": "en",
    "partOfSpeech": "adjective",
    "status": "enriched",
    "meanings": [
      {
        "definition": "Causing harm or damage, especially in a subtle or gradual way.",
        "example": "Prolonged exposure to the chemical had deleterious effects on the workers’ respiratory health.",
        "register": "formal",
        "tags": [
          "C1"
        ]
      }
    ],
    "synonyms": [
      "harmful",
      "detrimental",
      "injurious",
      "noxious"
    ],
    "antonymTerms": [],
    "relatedTerms": [],
    "translation": null
  },
  {
    "term": "enervate",
    "language": "en",
    "partOfSpeech": "verb",
    "status": "enriched",
    "meanings": [
      {
        "definition": "To deprive of strength, vitality, or energy; to weaken physically or mentally.",
        "example": "The oppressive heat enervated the hikers, forcing them to rest far more frequently than planned.",
        "register": "formal",
        "tags": [
          "C1"
        ]
      }
    ],
    "synonyms": [
      "weaken",
      "debilitate",
      "sap",
      "exhaust"
    ],
    "antonymTerms": [],
    "relatedTerms": [],
    "translation": null
  },
  {
    "term": "inscrutable",
    "language": "en",
    "partOfSpeech": "adjective",
    "status": "enriched",
    "meanings": [
      {
        "definition": "Impossible to understand or interpret; enigmatic.",
        "example": "The diplomat maintained an inscrutable expression throughout the tense negotiations.",
        "register": "formal",
        "tags": [
          "C1"
        ]
      }
    ],
    "synonyms": [
      "enigmatic",
      "impenetrable",
      "unfathomable"
    ],
    "antonymTerms": [],
    "relatedTerms": [],
    "translation": null
  },
  {
    "term": "magnanimous",
    "language": "en",
    "partOfSpeech": "adjective",
    "status": "enriched",
    "meanings": [
      {
        "definition": "Generous or forgiving, especially towards a rival or less powerful person.",
        "example": "In a magnanimous gesture, the victor offered clemency to those who had opposed her.",
        "register": "formal",
        "tags": [
          "C1"
        ]
      }
    ],
    "synonyms": [
      "generous",
      "benevolent",
      "noble",
      "gracious"
    ],
    "antonymTerms": [],
    "relatedTerms": [],
    "translation": null
  },
  {
    "term": "obsequious",
    "language": "en",
    "partOfSpeech": "adjective",
    "status": "enriched",
    "meanings": [
      {
        "definition": "Excessively eager to please or obey, especially in a way that lacks dignity or sincerity.",
        "example": "The obsequious assistant laughed at every remark the director made, no matter how banal.",
        "register": "formal",
        "tags": [
          "C1"
        ]
      }
    ],
    "synonyms": [
      "sycophantic",
      "servile",
      "fawning",
      "subservient"
    ],
    "antonymTerms": [],
    "relatedTerms": [],
    "translation": null
  },
  {
    "term": "perspicacious",
    "language": "en",
    "partOfSpeech": "adjective",
    "status": "enriched",
    "meanings": [
      {
        "definition": "Having a keen ability to notice and understand things that are not obvious; mentally sharp and perceptive.",
        "example": "A perspicacious reader will notice the subtle foreshadowing embedded in the opening chapter.",
        "register": "literary",
        "tags": [
          "C1"
        ]
      }
    ],
    "synonyms": [
      "perceptive",
      "astute",
      "discerning",
      "shrewd"
    ],
    "antonymTerms": [],
    "relatedTerms": [],
    "translation": null
  },
  {
    "term": "surreptitious",
    "language": "en",
    "partOfSpeech": "adjective",
    "status": "enriched",
    "meanings": [
      {
        "definition": "Done secretly, especially because it would not be approved of if discovered.",
        "example": "She cast a surreptitious glance at the confidential report left open on the desk.",
        "register": "formal",
        "tags": [
          "C1"
        ]
      }
    ],
    "synonyms": [
      "clandestine",
      "covert",
      "furtive",
      "stealthy"
    ],
    "antonymTerms": [],
    "relatedTerms": [],
    "translation": null
  },
  {
    "term": "truculent",
    "language": "en",
    "partOfSpeech": "adjective",
    "status": "enriched",
    "meanings": [
      {
        "definition": "Eager or quick to argue or fight; aggressively defiant.",
        "example": "The truculent union leader refused every compromise the management proposed.",
        "register": "formal",
        "tags": [
          "C1"
        ]
      }
    ],
    "synonyms": [
      "belligerent",
      "combative",
      "aggressive",
      "pugnacious"
    ],
    "antonymTerms": [],
    "relatedTerms": [],
    "translation": null
  },
  {
    "term": "abrogate",
    "language": "en",
    "partOfSpeech": "verb",
    "status": "stub",
    "meanings": [],
    "synonyms": [],
    "antonymTerms": [],
    "relatedTerms": [],
    "translation": null
  },
  {
    "term": "commensurate",
    "language": "en",
    "partOfSpeech": "adjective",
    "status": "stub",
    "meanings": [],
    "synonyms": [],
    "antonymTerms": [],
    "relatedTerms": [],
    "translation": null
  },
  {
    "term": "conflagration",
    "language": "en",
    "partOfSpeech": "noun",
    "status": "stub",
    "meanings": [],
    "synonyms": [],
    "antonymTerms": [],
    "relatedTerms": [],
    "translation": null
  },
  {
    "term": "disparate",
    "language": "en",
    "partOfSpeech": "adjective",
    "status": "stub",
    "meanings": [],
    "synonyms": [],
    "antonymTerms": [],
    "relatedTerms": [],
    "translation": null
  },
  {
    "term": "egregious",
    "language": "en",
    "partOfSpeech": "adjective",
    "status": "stub",
    "meanings": [],
    "synonyms": [],
    "antonymTerms": [],
    "relatedTerms": [],
    "translation": null
  },
  {
    "term": "inexorable",
    "language": "en",
    "partOfSpeech": "adjective",
    "status": "stub",
    "meanings": [],
    "synonyms": [],
    "antonymTerms": [],
    "relatedTerms": [],
    "translation": null
  },
  {
    "term": "loquacious",
    "language": "en",
    "partOfSpeech": "adjective",
    "status": "stub",
    "meanings": [],
    "synonyms": [],
    "antonymTerms": [],
    "relatedTerms": [],
    "translation": null
  },
  {
    "term": "obdurate",
    "language": "en",
    "partOfSpeech": "adjective",
    "status": "stub",
    "meanings": [],
    "synonyms": [],
    "antonymTerms": [],
    "relatedTerms": [],
    "translation": null
  },
  {
    "term": "parsimonious",
    "language": "en",
    "partOfSpeech": "adjective",
    "status": "stub",
    "meanings": [],
    "synonyms": [],
    "antonymTerms": [],
    "relatedTerms": [],
    "translation": null
  },
  {
    "term": "propensity",
    "language": "en",
    "partOfSpeech": "noun",
    "status": "stub",
    "meanings": [],
    "synonyms": [],
    "antonymTerms": [],
    "relatedTerms": [],
    "translation": null
  },
  {
    "term": "acquiesce",
    "language": "en",
    "partOfSpeech": "verb",
    "status": "stub",
    "meanings": [],
    "synonyms": [],
    "antonymTerms": [],
    "relatedTerms": [],
    "translation": null
  },
  {
    "term": "alacrity",
    "language": "en",
    "partOfSpeech": "noun",
    "status": "stub",
    "meanings": [],
    "synonyms": [],
    "antonymTerms": [],
    "relatedTerms": [],
    "translation": null
  },
  {
    "term": "capricious",
    "language": "en",
    "partOfSpeech": "adjective",
    "status": "stub",
    "meanings": [],
    "synonyms": [],
    "antonymTerms": [],
    "relatedTerms": [],
    "translation": null
  },
  {
    "term": "didactic",
    "language": "en",
    "partOfSpeech": "adjective",
    "status": "stub",
    "meanings": [],
    "synonyms": [],
    "antonymTerms": [],
    "relatedTerms": [],
    "translation": null
  },
  {
    "term": "elucidate",
    "language": "en",
    "partOfSpeech": "verb",
    "status": "stub",
    "meanings": [],
    "synonyms": [],
    "antonymTerms": [],
    "relatedTerms": [],
    "translation": null
  },
  {
    "term": "indefatigable",
    "language": "en",
    "partOfSpeech": "adjective",
    "status": "stub",
    "meanings": [],
    "synonyms": [],
    "antonymTerms": [],
    "relatedTerms": [],
    "translation": null
  },
  {
    "term": "malfeasance",
    "language": "en",
    "partOfSpeech": "noun",
    "status": "stub",
    "meanings": [],
    "synonyms": [],
    "antonymTerms": [],
    "relatedTerms": [],
    "translation": null
  },
  {
    "term": "pernicious",
    "language": "en",
    "partOfSpeech": "adjective",
    "status": "stub",
    "meanings": [],
    "synonyms": [],
    "antonymTerms": [],
    "relatedTerms": [],
    "translation": null
  },
  {
    "term": "sycophant",
    "language": "en",
    "partOfSpeech": "noun",
    "status": "stub",
    "meanings": [],
    "synonyms": [],
    "antonymTerms": [],
    "relatedTerms": [],
    "translation": null
  },
  {
    "term": "vindicate",
    "language": "en",
    "partOfSpeech": "verb",
    "status": "stub",
    "meanings": [],
    "synonyms": [],
    "antonymTerms": [],
    "relatedTerms": [],
    "translation": null
  }
]
